{
    "recording": "dynamic29647-19-8-Video-9b4f6a1a067fe51e15306b9628efea20",
    "trial": "461",
    "trial_type": "train",
    "first_label": "NaturalVideo",
    "label": "NaturalVideo",
    "ID": null,
    "sampling_freq": 30,
    "valid_frames": 300,
    "peaks": [
        36,
        80,
        126,
        184
    ],
    "n_peaks": 4,
    "segments_n_peaks": 5,
    "segments_bad_n": 0,
    "segments_avg_duration": 60.0,
    "segments": {
        "frame_start": [
            0,
            37,
            81,
            127,
            185
        ],
        "frame_end": [
            37,
            81,
            127,
            185,
            300
        ],
        "duration": [
            37,
            44,
            46,
            58,
            115
        ],
        "transition_start": [
            0,
            0,
            0,
            1,
            1
        ],
        "transition_end": [
            0,
            0,
            0,
            0,
            0
        ],
        "max_change": [
            28.43986365194722,
            40.75439512399149,
            43.579813025217426,
            6.343951984982725,
            27.92389443474529
        ],
        "is_static": [
            true,
            true,
            true,
            true,
            true
        ],
        "intensity_range": [
            235.1182665171012,
            203.3970237925122,
            215.32111891884168,
            203.54953060159033,
            219.26178911307034
        ],
        "margin_left": [
            0,
            0,
            0,
            0,
            0
        ],
        "margin_right": [
            0,
            0,
            0,
            0,
            0
        ],
        "margin_top": [
            0,
            0,
            0,
            0,
            0
        ],
        "margin_bottom": [
            0,
            0,
            0,
            0,
            0
        ],
        "background_color": [
            2.5098039215686274,
            2.5098039215686274,
            46.682352941176475,
            1.5058823529411764,
            11.545098039215686
        ],
        "background_proportion": [
            0.013916428024704391,
            0.023237864176432293,
            0.010845903037250868,
            0.013303700943439328,
            0.010637651410019188
        ],
        "is_uniform": [
            false,
            false,
            false,
            false,
            false
        ],
        "bad_properties": [
            false,
            false,
            false,
            false,
            false
        ]
    }
}