{
    "recording": "dynamic29234-6-9-Video-8744edeac3b4d1ce16b680916b5267ce",
    "trial": "381",
    "trial_type": "train",
    "first_label": "NaturalVideo",
    "label": "NaturalVideo",
    "ID": null,
    "sampling_freq": 30,
    "valid_frames": 300,
    "peaks": [
        85
    ],
    "n_peaks": 1,
    "segments_n_peaks": 2,
    "segments_bad_n": 0,
    "segments_avg_duration": 150.0,
    "segments": {
        "frame_start": [
            0,
            86
        ],
        "frame_end": [
            86,
            300
        ],
        "duration": [
            86,
            214
        ],
        "transition_start": [
            0,
            0
        ],
        "transition_end": [
            0,
            0
        ],
        "max_change": [
            259.29539218244577,
            404.5274538807182
        ],
        "is_static": [
            false,
            false
        ],
        "intensity_range": [
            203.27272033691406,
            201.53768920898438
        ],
        "margin_left": [
            0,
            0
        ],
        "margin_right": [
            0,
            0
        ],
        "margin_top": [
            0,
            0
        ],
        "margin_bottom": [
            0,
            0
        ],
        "background_color": [
            65.75686645507812,
            220.36077880859375
        ],
        "background_proportion": [
            0.018866784089210026,
            0.051411189116234296
        ],
        "is_uniform": [
            false,
            false
        ],
        "bad_properties": [
            false,
            false
        ]
    }
}