{
    "recording": "dynamic29515-10-12-Video-9b4f6a1a067fe51e15306b9628efea20",
    "trial": "350",
    "trial_type": "train",
    "first_label": "NaturalVideo",
    "label": "NaturalVideo",
    "ID": null,
    "sampling_freq": 30,
    "valid_frames": 324,
    "peaks": [
        53,
        134,
        188,
        242
    ],
    "n_peaks": 4,
    "segments_n_peaks": 5,
    "segments_bad_n": 0,
    "segments_avg_duration": 64.8,
    "segments": {
        "frame_start": [
            0,
            54,
            135,
            189,
            243
        ],
        "frame_end": [
            54,
            135,
            189,
            243,
            324
        ],
        "duration": [
            54,
            81,
            54,
            54,
            81
        ],
        "transition_start": [
            0,
            0,
            0,
            0,
            0
        ],
        "transition_end": [
            0,
            0,
            0,
            0,
            0
        ],
        "max_change": [
            457.2659265837402,
            2194.211818430505,
            418.0991162361695,
            391.15595115206287,
            1318.7633693093187
        ],
        "is_static": [
            false,
            false,
            false,
            false,
            false
        ],
        "intensity_range": [
            254.98461547154727,
            254.91086668912305,
            254.64247189067424,
            254.87182176846818,
            255.0
        ],
        "margin_left": [
            0,
            0,
            0,
            0,
            0
        ],
        "margin_right": [
            0,
            0,
            0,
            0,
            0
        ],
        "margin_top": [
            0,
            0,
            0,
            0,
            0
        ],
        "margin_bottom": [
            0,
            0,
            0,
            0,
            0
        ],
        "background_color": [
            133.01960784313724,
            135.02745098039216,
            133.01960784313724,
            115.95294117647059,
            132.0156862745098
        ],
        "background_proportion": [
            0.010327939633969652,
            0.00950063697595168,
            0.01036797040774473,
            0.010351958098234991,
            0.009735484182098799
        ],
        "is_uniform": [
            false,
            false,
            false,
            false,
            false
        ],
        "bad_properties": [
            false,
            false,
            false,
            false,
            false
        ]
    }
}