{
    "recording": "dynamic29513-3-5-Video-8744edeac3b4d1ce16b680916b5267ce",
    "trial": "714",
    "trial_type": "train",
    "first_label": "NaturalImages",
    "label": "NaturalImages",
    "ID": null,
    "sampling_freq": 30,
    "valid_frames": 326,
    "peaks": [
        17,
        33,
        51,
        67,
        84,
        100,
        116,
        131,
        150,
        166,
        183,
        199,
        212,
        228,
        246,
        261,
        278,
        294,
        310
    ],
    "n_peaks": 19,
    "segments_n_peaks": 20,
    "segments_bad_n": 0,
    "segments_avg_duration": 16.3,
    "segments": {
        "frame_start": [
            0,
            18,
            34,
            52,
            68,
            85,
            101,
            117,
            132,
            151,
            167,
            184,
            200,
            213,
            229,
            247,
            262,
            279,
            295,
            311
        ],
        "frame_end": [
            18,
            34,
            52,
            68,
            85,
            101,
            117,
            132,
            151,
            167,
            184,
            200,
            213,
            229,
            247,
            262,
            279,
            295,
            311,
            326
        ],
        "duration": [
            18,
            16,
            18,
            16,
            17,
            16,
            16,
            15,
            19,
            16,
            17,
            16,
            13,
            16,
            18,
            15,
            17,
            16,
            16,
            15
        ],
        "transition_start": [
            1,
            0,
            0,
            1,
            0,
            1,
            0,
            0,
            1,
            1,
            0,
            1,
            0,
            1,
            0,
            0,
            0,
            0,
            0,
            0
        ],
        "transition_end": [
            0,
            0,
            0,
            0,
            0,
            0,
            0,
            0,
            0,
            0,
            0,
            0,
            0,
            0,
            1,
            0,
            0,
            1,
            1,
            0
        ],
        "max_change": [
            0.0,
            44.10127155815803,
            0.10887910901356514,
            26.735612949863352,
            0.8032772248602669,
            8.526051893876708,
            6.655954046562126,
            0.7736087995080349,
            0.0,
            14.566584943189001,
            4.729707669130878,
            4.210126097461044,
            2.4897622322810093,
            1.9762198036896228,
            1.9398765218449827,
            2.749514075539941,
            4.809644062567865,
            7.578476330677379,
            0.0,
            7.512120532829107
        ],
        "is_static": [
            true,
            true,
            true,
            true,
            true,
            true,
            true,
            true,
            true,
            true,
            true,
            true,
            true,
            true,
            true,
            true,
            true,
            true,
            true,
            true
        ],
        "intensity_range": [
            0.0,
            237.25,
            1.21099853515625,
            247.4375,
            2.5262451171875,
            236.75,
            10.462928771972656,
            203.0,
            0.0,
            252.5625,
            6.336616516113281,
            239.0625,
            7.1826171875,
            226.625,
            7.7949981689453125,
            244.25,
            9.612602233886719,
            246.5625,
            0.0,
            194.45635986328125
        ],
        "margin_left": [
            64,
            0,
            64,
            0,
            64,
            0,
            64,
            0,
            64,
            0,
            64,
            0,
            64,
            0,
            64,
            0,
            64,
            0,
            64,
            0
        ],
        "margin_right": [
            64,
            4,
            64,
            0,
            64,
            0,
            64,
            0,
            64,
            0,
            64,
            0,
            64,
            0,
            64,
            0,
            64,
            0,
            64,
            2
        ],
        "margin_top": [
            36,
            0,
            36,
            0,
            36,
            0,
            36,
            0,
            36,
            0,
            36,
            0,
            36,
            0,
            36,
            0,
            36,
            0,
            36,
            0
        ],
        "margin_bottom": [
            36,
            0,
            36,
            0,
            36,
            0,
            36,
            0,
            36,
            0,
            36,
            0,
            36,
            0,
            36,
            0,
            36,
            0,
            36,
            0
        ],
        "background_color": [
            128.0,
            246.46273803710938,
            128.0,
            20.580392837524414,
            128.0,
            96.87843322753906,
            128.0,
            76.80000305175781,
            128.0,
            250.47842407226562,
            128.0,
            98.88627624511719,
            128.0,
            142.05490112304688,
            128.0,
            149.08236694335938,
            128.0,
            52.70588302612305,
            128.0,
            74.79216003417969
        ],
        "background_proportion": [
            0.9960862395221411,
            0.017779669231951387,
            0.9863828531224753,
            0.03213670710212895,
            0.9490132301942337,
            0.017898560637149848,
            0.8946510251350396,
            0.03216552926096494,
            0.9960862395221411,
            0.027035184988158708,
            0.942172258012058,
            0.009626601051220691,
            0.9321347892483338,
            0.015016344753550839,
            0.9547860951955492,
            0.013027615793867523,
            0.8949212308206737,
            0.01619805326582643,
            0.9960862395221413,
            0.027582806006042522
        ],
        "is_uniform": [
            true,
            false,
            true,
            false,
            true,
            false,
            true,
            false,
            true,
            false,
            true,
            false,
            true,
            false,
            true,
            false,
            true,
            false,
            true,
            false
        ],
        "bad_properties": [
            false,
            false,
            false,
            false,
            false,
            false,
            false,
            false,
            false,
            false,
            false,
            false,
            false,
            false,
            false,
            false,
            false,
            false,
            false,
            false
        ]
    }
}