{
    "recording": "dynamic29647-19-8-Video-9b4f6a1a067fe51e15306b9628efea20",
    "trial": "423",
    "trial_type": "final_test_main",
    "first_label": "NaturalVideo",
    "label": "NaturalVideo",
    "ID": null,
    "sampling_freq": 30,
    "valid_frames": 300,
    "peaks": [
        18,
        178,
        216,
        258
    ],
    "n_peaks": 4,
    "segments_n_peaks": 5,
    "segments_bad_n": 0,
    "segments_avg_duration": 60.0,
    "segments": {
        "frame_start": [
            0,
            19,
            179,
            217,
            259
        ],
        "frame_end": [
            19,
            179,
            217,
            259,
            300
        ],
        "duration": [
            19,
            160,
            38,
            42,
            41
        ],
        "transition_start": [
            0,
            0,
            0,
            0,
            0
        ],
        "transition_end": [
            0,
            0,
            0,
            0,
            0
        ],
        "max_change": [
            215.0332614893284,
            1214.9407222669172,
            360.44856162550786,
            411.7677646925946,
            794.7160733715505
        ],
        "is_static": [
            false,
            false,
            false,
            false,
            false
        ],
        "intensity_range": [
            246.09021744566542,
            254.99113932491687,
            254.78387320044303,
            239.13849938675145,
            255.00000000000003
        ],
        "margin_left": [
            0,
            0,
            0,
            0,
            0
        ],
        "margin_right": [
            0,
            0,
            0,
            0,
            0
        ],
        "margin_top": [
            0,
            0,
            0,
            0,
            0
        ],
        "margin_bottom": [
            0,
            0,
            0,
            0,
            0
        ],
        "background_color": [
            124.98823529411764,
            120.97254901960784,
            255.49803921568628,
            82.8235294117647,
            121.97647058823529
        ],
        "background_proportion": [
            0.018795080352247875,
            0.01442368825276698,
            0.0502188163891175,
            0.011158292255704248,
            0.01206312722306915
        ],
        "is_uniform": [
            false,
            false,
            false,
            false,
            false
        ],
        "bad_properties": [
            false,
            false,
            false,
            false,
            false
        ]
    }
}