{
    "recording": "dynamic29647-19-8-Video-9b4f6a1a067fe51e15306b9628efea20",
    "trial": "651",
    "trial_type": "train",
    "first_label": "NaturalVideo",
    "label": "NaturalVideo",
    "ID": null,
    "sampling_freq": 30,
    "valid_frames": 300,
    "peaks": [
        15,
        51,
        215
    ],
    "n_peaks": 3,
    "segments_n_peaks": 4,
    "segments_bad_n": 0,
    "segments_avg_duration": 75.0,
    "segments": {
        "frame_start": [
            0,
            16,
            52,
            216
        ],
        "frame_end": [
            16,
            52,
            216,
            300
        ],
        "duration": [
            16,
            36,
            164,
            84
        ],
        "transition_start": [
            0,
            0,
            0,
            1
        ],
        "transition_end": [
            0,
            0,
            0,
            0
        ],
        "max_change": [
            1.0436619902202375,
            7.496223382190071,
            83.18612897094648,
            2.591099210080165
        ],
        "is_static": [
            true,
            true,
            false,
            true
        ],
        "intensity_range": [
            110.00000000000001,
            116.74373051540546,
            144.32283848956845,
            116.375
        ],
        "margin_left": [
            0,
            0,
            0,
            0
        ],
        "margin_right": [
            0,
            0,
            0,
            0
        ],
        "margin_top": [
            0,
            0,
            0,
            0
        ],
        "margin_bottom": [
            0,
            0,
            0,
            0
        ],
        "background_color": [
            39.654901960784315,
            102.90196078431373,
            37.647058823529406,
            103.90588235294118
        ],
        "background_proportion": [
            0.029776891072591252,
            0.026396292227285973,
            0.02710776600411258,
            0.029643414968467726
        ],
        "is_uniform": [
            false,
            false,
            false,
            false
        ],
        "bad_properties": [
            false,
            false,
            false,
            false
        ]
    }
}