{
    "recording": "dynamic29623-4-9-Video-9b4f6a1a067fe51e15306b9628efea20",
    "trial": "530",
    "trial_type": "final_test_bonus",
    "first_label": "NaturalVideo",
    "label": "NaturalVideo",
    "ID": null,
    "sampling_freq": 30,
    "valid_frames": 300,
    "peaks": [
        110
    ],
    "n_peaks": 1,
    "segments_n_peaks": 2,
    "segments_bad_n": 0,
    "segments_avg_duration": 150.0,
    "segments": {
        "frame_start": [
            0,
            111
        ],
        "frame_end": [
            111,
            300
        ],
        "duration": [
            111,
            189
        ],
        "transition_start": [
            0,
            0
        ],
        "transition_end": [
            0,
            0
        ],
        "max_change": [
            17.45603482770196,
            43.026333582838284
        ],
        "is_static": [
            true,
            true
        ],
        "intensity_range": [
            220.34895088099597,
            215.64157465582383
        ],
        "margin_left": [
            0,
            0
        ],
        "margin_right": [
            0,
            0
        ],
        "margin_top": [
            0,
            0
        ],
        "margin_bottom": [
            0,
            0
        ],
        "background_color": [
            138.0392156862745,
            81.81960784313725
        ],
        "background_proportion": [
            0.011435385580893435,
            0.016808350039958172
        ],
        "is_uniform": [
            false,
            false
        ],
        "bad_properties": [
            false,
            false
        ]
    }
}