{
    "recording": "dynamic29515-10-12-Video-9b4f6a1a067fe51e15306b9628efea20",
    "trial": "565",
    "trial_type": "train",
    "first_label": "NaturalVideo",
    "label": "NaturalVideo",
    "ID": null,
    "sampling_freq": 30,
    "valid_frames": 300,
    "peaks": [
        7,
        52,
        92,
        139,
        194,
        232
    ],
    "n_peaks": 6,
    "segments_n_peaks": 7,
    "segments_bad_n": 0,
    "segments_avg_duration": 42.857142857142854,
    "segments": {
        "frame_start": [
            0,
            8,
            53,
            93,
            140,
            195,
            233
        ],
        "frame_end": [
            8,
            53,
            93,
            140,
            195,
            233,
            300
        ],
        "duration": [
            8,
            45,
            40,
            47,
            55,
            38,
            67
        ],
        "transition_start": [
            0,
            0,
            0,
            0,
            0,
            0,
            0
        ],
        "transition_end": [
            0,
            0,
            0,
            0,
            0,
            0,
            0
        ],
        "max_change": [
            302.7631802083849,
            687.7647931552644,
            677.0592493201128,
            1048.6760865353046,
            444.9014261094437,
            1074.8548857786523,
            2916.1646523328577
        ],
        "is_static": [
            false,
            false,
            false,
            false,
            false,
            false,
            false
        ],
        "intensity_range": [
            250.85635019303288,
            245.1161174739044,
            249.61749942248298,
            252.07740933978258,
            235.49603909906048,
            208.26063070980163,
            251.75
        ],
        "margin_left": [
            0,
            0,
            0,
            0,
            0,
            0,
            0
        ],
        "margin_right": [
            0,
            0,
            0,
            0,
            0,
            0,
            0
        ],
        "margin_top": [
            0,
            0,
            0,
            0,
            0,
            0,
            0
        ],
        "margin_bottom": [
            0,
            0,
            0,
            0,
            0,
            0,
            0
        ],
        "background_color": [
            13.552941176470588,
            57.725490196078425,
            32.627450980392155,
            23.5921568627451,
            61.74117647058823,
            255.49803921568628,
            6.525490196078431
        ],
        "background_proportion": [
            0.02037366231282552,
            0.011490433304398109,
            0.008376439412434926,
            0.01962053014876995,
            0.012639825994318137,
            0.12676439787212218,
            0.0453948974609375
        ],
        "is_uniform": [
            false,
            false,
            false,
            false,
            false,
            false,
            false
        ],
        "bad_properties": [
            false,
            false,
            false,
            false,
            false,
            false,
            false
        ]
    }
}