{
    "label": "Gabor",
    "ID": "v142850",
    "valid_frames": 300,
    "sampling_freq": 30,
    "segments": {
        "frame_start": [
            0,
            25,
            50,
            75,
            100,
            125,
            150,
            175,
            200,
            225,
            250,
            275
        ],
        "frame_end": [
            25,
            50,
            75,
            100,
            125,
            150,
            175,
            200,
            225,
            250,
            275,
            300
        ],
        "bad_properties": [
            false,
            false,
            false,
            false,
            false,
            false,
            false,
            false,
            false,
            false,
            false,
            false
        ],
        "segment_ID": [
            "s978552",
            "s553738",
            "s926514",
            "s211538",
            "s730467",
            "s629375",
            "s481172",
            "s270648",
            "s625367",
            "s380363",
            "s360830",
            "s101309"
        ]
    },
    "duplicates": {
        "dynamic29514-2-9-Video-8744edeac3b4d1ce16b680916b5267ce": {
            "trials": [
                "24",
                "117",
                "166",
                "38",
                "402",
                "56",
                "513",
                "250",
                "97",
                "472"
            ],
            "n": 10
        },
        "dynamic29712-5-9-Video-9b4f6a1a067fe51e15306b9628efea20": {
            "trials": [
                "24",
                "117",
                "166",
                "38",
                "402",
                "56",
                "513",
                "250",
                "97",
                "472"
            ],
            "n": 10
        }
    }
}