{
    "label": "NaturalVideo",
    "ID": "v675670",
    "valid_frames": 300,
    "sampling_freq": 30,
    "segments": {
        "frame_start": [
            0,
            64,
            230
        ],
        "frame_end": [
            64,
            230,
            300
        ],
        "bad_properties": [
            false,
            false,
            false
        ]
    },
    "duplicates": {
        "dynamic29623-4-9-Video-9b4f6a1a067fe51e15306b9628efea20": {
            "trials": [
                "286"
            ],
            "n": 1
        },
        "dynamic29234-6-9-Video-8744edeac3b4d1ce16b680916b5267ce": {
            "trials": [
                "271"
            ],
            "n": 1
        }
    }
}