{
    "label": "NaturalVideo",
    "ID": "v309478",
    "valid_frames": 300,
    "sampling_freq": 30,
    "segments": {
        "frame_start": [
            0,
            57,
            157,
            245
        ],
        "frame_end": [
            57,
            157,
            245,
            300
        ],
        "bad_properties": [
            false,
            false,
            false,
            false
        ]
    },
    "duplicates": {
        "dynamic29228-2-10-Video-8744edeac3b4d1ce16b680916b5267ce": {
            "trials": [
                "90"
            ],
            "n": 1
        },
        "dynamic29755-2-8-Video-9b4f6a1a067fe51e15306b9628efea20": {
            "trials": [
                "99"
            ],
            "n": 1
        }
    }
}