{
    "label": "NaturalVideo",
    "ID": "v241699",
    "valid_frames": 300,
    "sampling_freq": 30,
    "segments": {
        "frame_start": [
            0,
            116,
            165
        ],
        "frame_end": [
            116,
            165,
            300
        ],
        "bad_properties": [
            false,
            false,
            false
        ]
    },
    "duplicates": {
        "dynamic29514-2-9-Video-8744edeac3b4d1ce16b680916b5267ce": {
            "trials": [
                "116",
                "415",
                "298",
                "551",
                "231",
                "74",
                "79",
                "114",
                "640",
                "227"
            ],
            "n": 10
        },
        "dynamic29712-5-9-Video-9b4f6a1a067fe51e15306b9628efea20": {
            "trials": [
                "116",
                "298",
                "415",
                "231",
                "551",
                "74",
                "79",
                "114",
                "640",
                "227"
            ],
            "n": 10
        }
    }
}