{
    "recording": "dynamic29228-2-10-Video-8744edeac3b4d1ce16b680916b5267ce",
    "trial": "620",
    "trial_type": "train",
    "first_label": "PinkNoise",
    "label": "PinkNoise",
    "ID": null,
    "sampling_freq": 30,
    "valid_frames": 324,
    "peaks": [
        26,
        53,
        80,
        107,
        134,
        161,
        188,
        215,
        242,
        269,
        296
    ],
    "n_peaks": 11,
    "segments_n_peaks": 12,
    "segments_bad_n": 0,
    "segments_avg_duration": 27.0,
    "segments": {
        "frame_start": [
            0,
            27,
            54,
            81,
            108,
            135,
            162,
            189,
            216,
            243,
            270,
            297
        ],
        "frame_end": [
            27,
            54,
            81,
            108,
            135,
            162,
            189,
            216,
            243,
            270,
            297,
            324
        ],
        "duration": [
            27,
            27,
            27,
            27,
            27,
            27,
            27,
            27,
            27,
            27,
            27,
            27
        ],
        "transition_start": [
            0,
            0,
            0,
            0,
            0,
            0,
            0,
            0,
            0,
            0,
            0,
            0
        ],
        "transition_end": [
            0,
            0,
            0,
            0,
            0,
            0,
            0,
            0,
            0,
            0,
            0,
            0
        ],
        "max_change": [
            456.16320547824193,
            445.27271686667893,
            508.74161299727086,
            421.7435693292931,
            405.32799543993565,
            403.5500114377367,
            400.79836152475247,
            404.00671322963535,
            438.0063652468412,
            390.9868140156125,
            388.7462801078943,
            472.541170335723
        ],
        "is_static": [
            false,
            false,
            false,
            false,
            false,
            false,
            false,
            false,
            false,
            false,
            false,
            false
        ],
        "intensity_range": [
            254.83009338378906,
            254.98684692382812,
            254.81715393066406,
            253.67877197265625,
            254.7650909423828,
            254.36514282226562,
            254.81134033203125,
            254.16258239746094,
            254.99713134765625,
            254.86007690429688,
            253.71315002441406,
            255.0
        ],
        "margin_left": [
            0,
            0,
            0,
            0,
            0,
            0,
            0,
            0,
            0,
            0,
            0,
            0
        ],
        "margin_right": [
            0,
            0,
            0,
            0,
            0,
            0,
            0,
            0,
            0,
            0,
            0,
            0
        ],
        "margin_top": [
            0,
            0,
            0,
            0,
            0,
            0,
            0,
            0,
            0,
            0,
            0,
            0
        ],
        "margin_bottom": [
            0,
            0,
            0,
            0,
            0,
            0,
            0,
            0,
            0,
            0,
            0,
            0
        ],
        "background_color": [
            126.99607849121094,
            123.98431396484375,
            122.98039245605469,
            118.96470642089844,
            137.03530883789062,
            129.00393676757812,
            126.99607849121094,
            139.04315185546875,
            128.0,
            128.0,
            131.01177978515625,
            124.98823547363281
        ],
        "background_proportion": [
            0.010536100285600822,
            0.009751497072843316,
            0.010359964870491995,
            0.010472051043743068,
            0.010135792523989851,
            0.010488063354207506,
            0.01029591562863424,
            0.01042401411234975,
            0.010632093348808864,
            0.010712154292700497,
            0.009943644798416583,
            0.010215854076312045
        ],
        "is_uniform": [
            false,
            false,
            false,
            false,
            false,
            false,
            false,
            false,
            false,
            false,
            false,
            false
        ],
        "bad_properties": [
            false,
            false,
            false,
            false,
            false,
            false,
            false,
            false,
            false,
            false,
            false,
            false
        ]
    }
}