{
    "recording": "dynamic29712-5-9-Video-9b4f6a1a067fe51e15306b9628efea20",
    "trial": "420",
    "trial_type": "train",
    "first_label": "GaussianDot",
    "label": "GaussianDot",
    "ID": null,
    "sampling_freq": 30,
    "valid_frames": 315,
    "peaks": [
        8,
        17,
        26,
        35,
        44,
        53,
        62,
        71,
        80,
        89,
        98,
        107,
        116,
        125,
        134,
        143,
        152,
        161,
        170,
        179,
        188,
        197,
        206,
        215,
        224,
        233,
        242,
        251,
        260,
        269,
        278,
        287,
        296,
        305
    ],
    "n_peaks": 34,
    "segments_n_peaks": 35,
    "segments_bad_n": 0,
    "segments_avg_duration": 9.0,
    "segments": {
        "frame_start": [
            0,
            9,
            18,
            27,
            36,
            45,
            54,
            63,
            72,
            81,
            90,
            99,
            108,
            117,
            126,
            135,
            144,
            153,
            162,
            171,
            180,
            189,
            198,
            207,
            216,
            225,
            234,
            243,
            252,
            261,
            270,
            279,
            288,
            297,
            306
        ],
        "frame_end": [
            9,
            18,
            27,
            36,
            45,
            54,
            63,
            72,
            81,
            90,
            99,
            108,
            117,
            126,
            135,
            144,
            153,
            162,
            171,
            180,
            189,
            198,
            207,
            216,
            225,
            234,
            243,
            252,
            261,
            270,
            279,
            288,
            297,
            306,
            315
        ],
        "duration": [
            9,
            9,
            9,
            9,
            9,
            9,
            9,
            9,
            9,
            9,
            9,
            9,
            9,
            9,
            9,
            9,
            9,
            9,
            9,
            9,
            9,
            9,
            9,
            9,
            9,
            9,
            9,
            9,
            9,
            9,
            9,
            9,
            9,
            9,
            9
        ],
        "transition_start": [
            0,
            0,
            0,
            0,
            0,
            0,
            0,
            0,
            0,
            0,
            0,
            0,
            0,
            0,
            0,
            0,
            0,
            0,
            0,
            0,
            0,
            0,
            0,
            0,
            0,
            1,
            1,
            1,
            1,
            1,
            1,
            1,
            1,
            1,
            1
        ],
        "transition_end": [
            0,
            0,
            0,
            0,
            0,
            0,
            0,
            0,
            0,
            0,
            0,
            0,
            0,
            0,
            0,
            0,
            0,
            0,
            0,
            0,
            0,
            0,
            0,
            0,
            0,
            0,
            0,
            0,
            0,
            0,
            0,
            0,
            0,
            0,
            0
        ],
        "max_change": [
            7.102371745055848e-28,
            0.07949891592567068,
            0.40719240869255874,
            0.7698487265331786,
            1.6234677538231586,
            3.2615754508247745,
            2.490498931578911,
            4.181491654485281,
            5.6670197862388925,
            2.740675441676781,
            15.133927066622467,
            10.331604880316263,
            12.291987522907396,
            14.431374353432908,
            11.376332907969532,
            13.786097482948476,
            17.61067074850909,
            24.27436853992622,
            26.62966064624646,
            30.281748554333596,
            33.48711650027998,
            40.57232816010718,
            41.36955860155085,
            45.19815929373092,
            49.407984715164126,
            2.0345652862816926e-28,
            2.665473347530108e-28,
            1.9887306680138148e-28,
            6.801407261125048e-28,
            1.8231452031774495e-29,
            1.165542201456261e-28,
            1.020260104085842e-28,
            2.8660961858836297e-29,
            7.043651371506723e-28,
            1.9602799749064625e-29
        ],
        "is_static": [
            true,
            true,
            true,
            true,
            true,
            true,
            true,
            true,
            true,
            true,
            true,
            true,
            true,
            true,
            true,
            true,
            true,
            true,
            true,
            true,
            true,
            true,
            true,
            true,
            true,
            true,
            true,
            true,
            true,
            true,
            true,
            true,
            true,
            true,
            true
        ],
        "intensity_range": [
            127.32812500000003,
            127.421875,
            127.70871811702936,
            130.2215842799985,
            130.2859985424825,
            127.58283143289896,
            127.40625,
            127.45312500000003,
            136.46273963237797,
            125.90625000000004,
            127.65390861114881,
            139.6492928682183,
            141.57743304384758,
            142.6270936781079,
            126.03125,
            126.10937500000001,
            125.92187500000004,
            126.45312500000004,
            125.82812500000004,
            126.32812500000003,
            125.90625000000004,
            152.39403256862448,
            153.39887084991602,
            155.32826088315767,
            126.87500000000003,
            127.484375,
            125.75000000000004,
            126.921875,
            127.04687500000003,
            126.046875,
            126.90625,
            125.75000000000003,
            126.875,
            126.34375000000007,
            126.90625
        ],
        "margin_left": [
            28,
            34,
            44,
            6,
            12,
            9,
            18,
            18,
            34,
            40,
            44,
            15,
            39,
            15,
            6,
            14,
            9,
            47,
            41,
            12,
            31,
            41,
            22,
            40,
            25,
            47,
            25,
            34,
            2,
            9,
            31,
            36,
            9,
            13,
            25
        ],
        "margin_right": [
            21,
            15,
            6,
            44,
            38,
            41,
            31,
            31,
            15,
            9,
            5,
            33,
            9,
            33,
            43,
            34,
            41,
            2,
            9,
            38,
            18,
            5,
            25,
            5,
            25,
            2,
            20,
            9,
            47,
            15,
            17,
            9,
            14,
            22,
            24
        ],
        "margin_top": [
            17,
            4,
            11,
            11,
            20,
            14,
            20,
            1,
            1,
            1,
            4,
            10,
            13,
            4,
            4,
            8,
            17,
            4,
            21,
            17,
            11,
            15,
            14,
            8,
            4,
            17,
            14,
            16,
            8,
            7,
            10,
            12,
            4,
            1,
            1
        ],
        "margin_bottom": [
            4,
            17,
            11,
            11,
            1,
            7,
            1,
            20,
            20,
            20,
            17,
            11,
            7,
            16,
            17,
            14,
            4,
            17,
            1,
            4,
            11,
            4,
            6,
            11,
            17,
            4,
            6,
            4,
            14,
            13,
            11,
            7,
            12,
            19,
            20
        ],
        "background_color": [
            128.0,
            128.0,
            128.0,
            128.0,
            128.0,
            128.0,
            128.0,
            128.0,
            128.0,
            128.0,
            128.0,
            128.0,
            128.0,
            128.0,
            128.0,
            128.0,
            128.0,
            128.0,
            128.0,
            128.0,
            128.0,
            128.0,
            128.0,
            128.0,
            128.0,
            128.0,
            128.0,
            128.0,
            128.0,
            128.0,
            128.0,
            128.0,
            128.0,
            128.0,
            128.0
        ],
        "background_proportion": [
            0.6930287679036483,
            0.6900985152633127,
            0.7319386800130234,
            0.673717922634551,
            0.7644116436993661,
            0.6744865134910325,
            0.7194971155237294,
            0.712051391601565,
            0.758599175347225,
            0.7655164930555582,
            0.7095534713180003,
            0.712003354673035,
            0.6537825972945625,
            0.7222832573784748,
            0.7378952591507549,
            0.7247331407335095,
            0.732755307798035,
            0.7482712357132549,
            0.7547081841362875,
            0.7244449191623289,
            0.7132523148148173,
            0.6970638699001761,
            0.7090731020326994,
            0.6652153862847245,
            0.6732855902777801,
            0.7375590006510443,
            0.7310740152994817,
            0.6934611002604192,
            0.7137807210286484,
            0.7315063476562526,
            0.6683858235677107,
            0.7310740152994817,
            0.6930287679036483,
            0.7691192626953153,
            0.7254536946614609
        ],
        "is_uniform": [
            false,
            false,
            false,
            false,
            false,
            false,
            false,
            false,
            false,
            false,
            false,
            false,
            false,
            false,
            false,
            false,
            false,
            false,
            false,
            false,
            false,
            false,
            false,
            false,
            false,
            false,
            false,
            false,
            false,
            false,
            false,
            false,
            false,
            false,
            false
        ],
        "bad_properties": [
            false,
            false,
            false,
            false,
            false,
            false,
            false,
            false,
            false,
            false,
            false,
            false,
            false,
            false,
            false,
            false,
            false,
            false,
            false,
            false,
            false,
            false,
            false,
            false,
            false,
            false,
            false,
            false,
            false,
            false,
            false,
            false,
            false,
            false,
            false
        ]
    }
}