{
    "recording": "dynamic29156-11-10-Video-8744edeac3b4d1ce16b680916b5267ce",
    "trial": "39",
    "trial_type": "train",
    "first_label": "NaturalVideo",
    "label": "NaturalVideo",
    "ID": null,
    "sampling_freq": 30,
    "valid_frames": 300,
    "n_peaks": 4,
    "segments_n_peaks": 5,
    "segments_bad_n": 0,
    "segments_avg_duration": 60.0,
    "segments": {
        "frame_start": [
            0,
            38,
            109,
            185,
            260
        ],
        "frame_end": [
            38,
            109,
            185,
            260,
            300
        ],
        "duration": [
            38,
            71,
            76,
            75,
            40
        ],
        "transition_start": [
            0,
            0,
            0,
            0,
            1
        ],
        "transition_end": [
            0,
            0,
            0,
            0,
            0
        ],
        "max_change": [
            403.78696436674795,
            48.19348331860752,
            639.5010691568164,
            227.88270179552424,
            3.1022439581186996
        ],
        "is_static": [
            false,
            true,
            false,
            false,
            true
        ],
        "intensity_range": [
            214.25540161132812,
            185.8784637451172,
            249.3265838623047,
            210.375,
            242.9375
        ],
        "margin_left": [
            0,
            8,
            0,
            0,
            0
        ],
        "margin_right": [
            0,
            13,
            0,
            0,
            0
        ],
        "margin_top": [
            0,
            0,
            0,
            0,
            0
        ],
        "margin_bottom": [
            0,
            0,
            0,
            0,
            0
        ],
        "background_color": [
            4.5176472663879395,
            4.5176472663879395,
            4.5176472663879395,
            23.5921573638916,
            8.533333778381348
        ],
        "background_proportion": [
            0.12412490246078366,
            0.192887223686125,
            0.10026129266138001,
            0.02150133049164861,
            0.05003970191756127
        ],
        "is_uniform": [
            false,
            false,
            false,
            false,
            false
        ],
        "bad_properties": [
            false,
            false,
            false,
            false,
            false
        ]
    }
}